Workbook

Sheet Cover
B2: TUSCANY VILLAGE SELF STORAGE
B5: User Acceptance Testing (UAT) Plan & Test Cases
B8: Project Information
B10: Project Name | C10: Tuscany Village Self Storage — Management Platform
B11: Document Type | C11: User Acceptance Testing (UAT) Plan
B12: Document Version | C12: 1.0
B13: Release / Build | C13: Production candidate
B14: Prepared By | C14: Hive Media Studio
B15: Prepared For | C15: David (Tuscany Village Self Storage)
B16: Date Issued | C16: 2026-06-02
B17: Production URL | C17: https://tuscany-storage.onrender.com
B18: Repository | C18: github.com/Shiru04/tuscany-storage
B19: Test Environment | C19: Staging — production-equivalent data
B20: Browser Support | C20: Chrome (latest), Safari (latest), Edge (latest), Firefox (latest)
B21: Mobile Support | C21: iOS Safari, Android Chrome (responsive)
B24: Final Acceptance Sign-Off
B25: Role | C25: Name | D25: Signature | E25: Date
B26: Client / Product Owner
B27: Project Manager
B28: QA Lead
B29: Technical Lead

Sheet Instructions
B2: How to Use This Document
B4: This workbook contains the User Acceptance Test (UAT) cases for Tuscany Village Self Storage. Its purpose is to verify, prior to production release, that every user-facing feature behaves as expected from the perspective of the end user (Admin, Tenant, Public visitor). Each test case below describes a scenario, the exact steps to reproduce, and the expected outcome. The tester executes each case and records the result.
B9: Testing Workflow
B10: 1. Open the 'Test Environment' tab and confirm test credentials and URLs are accessible.
B11: 2. Open the 'Test Cases' tab. Filter by module if you want to focus on one area.
B12: 3. For each test case: read Preconditions, execute the Steps, compare against Expected Result.
B13: 4. Record what actually happened in 'Actual Result' and select a Status from the dropdown.
B14: 5. If Status = Fail or Blocked: open the 'Defect Log' tab and create an entry. Reference its Defect ID back in the test case row.
B15: 6. Fill in Tester Name and Test Date for every case you execute.
B16: 7. The 'Summary' tab automatically counts results — no manual update needed.
B17: 8. When all Critical and High cases pass, parties sign the 'Cover' tab to release the build to production.
B20: Status Definitions
B21: Status | C21: Meaning
B22: Not Run | C22: Test has not been executed yet (default state).
B23: Pass | C23: Actual result matches expected result. No defect.
B24: Fail | C24: Actual result does not match expected result. A defect must be raised.
B25: Blocked | C25: Test cannot be executed because of an environmental issue or dependency on a failed earlier test.
B26: N/A | C26: Test is not applicable to this release (feature disabled, deferred, etc.). Add reason in Comments.
B29: Defect Severity Definitions
B30: Severity | C30: Meaning
B31: Critical | C31: Blocks core business operation. No workaround. Examples: cannot log in, payments fail across the board, gate access broken for all tenants.
B32: High | C32: Major function broken or significantly degraded. Workaround exists but is painful. Must be fixed before release.
B33: Medium | C33: Feature partially works or has noticeable defect that does not block primary flow. Should be fixed soon.
B34: Low | C34: Cosmetic issue, minor inconvenience, or edge case. Can be deferred.
B37: Test Case Priority
B38: Priority | C38: Meaning
B39: Critical | C39: Must pass for release. Covers core business functions (auth, payment, gate access, move-in).
B40: High | C40: Must pass for release. Covers major features users rely on daily.
B41: Medium | C41: Should pass. Covers secondary flows. Failures discussed before release.
B42: Low | C42: Nice to have. Edge cases, cosmetics, rare flows.
B45: Release / Sign-Off Criteria
B46: • 100% of Critical-priority test cases have Status = Pass.
B47: • ≥ 95% of High-priority test cases have Status = Pass.
B48: • No open defects with Severity = Critical or High.
B49: • All Critical / High defects raised during testing are either Fixed-Verified or Accepted-with-Workaround.
B50: • All sign-off rows on the Cover sheet are completed.

Sheet Test Environment
B2: Test Environment & Credentials
B4: URLs
B5: Production | C5: https://tuscany-storage.onrender.com
B6: Admin Login | C6: https://tuscany-storage.onrender.com/login
B7: Tenant Portal | C7: https://tuscany-storage.onrender.com/portal
B8: Public Site | C8: https://tuscany-storage.onrender.com
B9: Reserve Unit (Move-In Funnel) | C9: https://tuscany-storage.onrender.com/reserve
B12: Test Credentials
B13: Role | C13: Email / Username | D13: Password | E13: Notes
B14: Admin | C14: admin@tuscanystorage.com | D14: (provided separately) | E14: Full admin access
B15: Tenant 1 | C15: john@example.com | D15: tenant123 | E15: Active tenant with unit + autopay on
B16: Tenant 2 | C16: jane@example.com | D16: tenant123 | E16: Active tenant with balance owed
B17: Tenant 3 | C17: bob@example.com | D17: tenant123 | E17: Delinquent tenant (for lockout tests)
B20: Stripe Test Cards (TEST mode only)
B21: Card Number | C21: Expected Behaviour | D21: Notes (use any future expiry, any CVC, any ZIP)
B22: 4242 4242 4242 4242 | C22: Successful charge | D22: Default success card.
B23: 4000 0025 0000 3155 | C23: Requires 3D Secure | D23: Tests Strong Customer Authentication challenge.
B24: 4000 0000 0000 9995 | C24: Decline — insufficient funds | D24: Used for decline-handling tests.
B25: 4000 0000 0000 0002 | C25: Decline — generic | D25: Generic decline.
B26: 4000 0000 0000 0341 | C26: Attach succeeds, future charge fails | D26: Use for autopay failure tests.
B29: Tester Prerequisites
B30: • Working email inbox for receiving test confirmations and receipts (e.g., +uat alias on a real address).
B31: • Mobile phone capable of receiving SMS (for text-to-open and SMS notification tests).
B32: • Modern browser (Chrome / Edge / Safari latest).
B33: • Access to the staging environment URL above.
B34: • Stripe test cards listed in this sheet — do NOT use real credit cards.
B35: • (For PDK / gate tests) coordination with the on-site PDK device, or use of the sandbox simulator.

Sheet Test Cases
A1: Test ID | B1: Module | C1: Sub-Module | D1: Priority | E1: Test Title | F1: Preconditions | G1: Test Steps | H1: Test Data | I1: Expected Result | J1: Actual Result | K1: Status | L1: Severity | M1: Tester | N1: Test Date | O1: Comments | P1: Defect ID
A2: AUTH-001 | B2: Authentication | C2: Login | D2: Critical | E2: Admin can log in with valid credentials | F2: Admin account exists. | G2: 1. Navigate to /login. 2. Enter admin email and password. 3. Click Sign In. | H2: admin@tuscanystorage.com / valid password | I2: User is redirected to /admin dashboard. Sidebar nav is visible. Session is established. | K2: Not Run
A3: AUTH-002 | B3: Authentication | C3: Login | D3: Critical | E3: Tenant can log in and lands on portal | F3: Tenant account exists with assigned unit. | G3: 1. Navigate to /login. 2. Enter tenant email + password. 3. Click Sign In. | H3: john@example.com / tenant123 | I3: User is redirected to /portal. Dashboard shows tenant's name, balance, and rentals. | K3: Not Run
A4: AUTH-003 | B4: Authentication | C4: Login | D4: High | E4: Login fails with wrong password | F4: Tenant account exists. | G4: 1. Navigate to /login. 2. Enter valid email + wrong password. 3. Click Sign In. | H4: john@example.com / WrongPass | I4: Error message displayed (generic 'invalid credentials'). User stays on login page. No session created. | K4: Not Run
A5: AUTH-004 | B5: Authentication | C5: Login | D5: Medium | E5: Login fails with non-existent email | F5: — | G5: 1. Navigate to /login. 2. Enter random email + any password. 3. Click Sign In. | H5: noone@example.com / anything | I5: Same generic error as wrong password (no enumeration of valid emails). | K5: Not Run
A6: AUTH-005 | B6: Authentication | C6: Password reset | D6: High | E6: Tenant can request password reset | F6: Tenant account exists. | G6: 1. Click 'Forgot Password' on login screen. 2. Enter tenant email. 3. Click Send. | H6: john@example.com | I6: Confirmation screen shown. Reset email arrives at inbox within 2 minutes with reset link. | K6: Not Run
A7: AUTH-006 | B7: Authentication | C7: Password reset | D7: High | E7: Reset link sets a new password | F7: Reset email received within last 24h. | G7: 1. Open the reset link. 2. Enter new password (meets strength rules) twice. 3. Submit. 4. Log in with the new password. | H7: Strong new password (e.g., Tuscany!2026) | I7: Password is updated. Login with new password succeeds. Login with old password fails. | K7: Not Run
A8: AUTH-007 | B8: Authentication | C8: Password reset | D8: Medium | E8: Reset link expires after use | F8: Password just reset using a link. | G8: 1. Open the same reset link a second time. | H8: — | I8: Link is rejected. Page shows 'link expired/invalid' message. | K8: Not Run
A9: AUTH-008 | B9: Authentication | C9: Logout | D9: High | E9: User can log out and session ends | F9: Logged in as any role. | G9: 1. Click user menu in top-right. 2. Click Sign Out. 3. Try to navigate to /admin or /portal. | H9: — | I9: Redirected to /login. Protected pages redirect to login when accessed. | K9: Not Run
A10: AUTH-009 | B10: Authentication | C10: Session | D10: Medium | E10: Admin route blocks tenant role | F10: Logged in as tenant. | G10: 1. While logged in as tenant, navigate directly to /admin in URL bar. | H10: — | I10: Tenant is redirected away (to /portal or /login). No admin content rendered. | K10: Not Run
A11: PUB-001 | B11: Public Site | C11: Home | D11: Medium | E11: Public homepage loads and displays facility info | F11: — | G11: 1. Open the production URL in a fresh browser. | H11: — | I11: Homepage loads. Facility name, hero copy, and CTA buttons are visible. No JS errors in console. | K11: Not Run
A12: PUB-002 | B12: Public Site | C12: Units listing | D12: High | E12: Available units are displayed publicly | F12: At least one unit has status = available. | G12: 1. From homepage, click 'Units' or 'Reserve'. 2. Browse the unit grid. | H12: — | I12: Units shown with size, monthly price, features. Filters by size work. Sold-out / occupied units do not appear as available. | K12: Not Run
A13: PUB-003 | B13: Public Site | C13: Size guide | D13: Low | E13: Size guide page renders | F13: — | G13: 1. Navigate to /size-guide. | H13: — | I13: Visual comparisons for 5x5, 5x10, 10x10, 10x15, 10x20 displayed. Page is responsive on mobile. | K13: Not Run
... A147: XCUT-007 | B147: Cross-cutting | C147: Role check on admin APIs | D147: Critical | E147: Tenant role cannot call admin APIs | F147: Tenant session token. | G147: 1. Call admin API with tenant session. | H147: — | I147: 403 response. No data leaked. | K147: Not Run

Sheet Defect Log
A1: Defect ID | B1: Linked Test ID | C1: Module | D1: Title | E1: Severity | F1: Status | G1: Steps to Reproduce | H1: Expected | I1: Actual | J1: Environment / Browser | K1: Reported By | L1: Reported Date | M1: Assigned To | N1: Fix Notes | O1: Verified By | P1: Verified Date
A2: DEF-001
A3: DEF-002
A4: DEF-003
A5: DEF-004
A6: DEF-005
A7: DEF-006
A8: DEF-007
A9: DEF-008
A10: DEF-009
A11: DEF-010
A12: DEF-011
A13: DEF-012
... A31: DEF-030

Sheet Summary
B2: Test Execution Summary
B4: Status | C4: Count | D4: % of Total
B5: Not Run | C5: =COUNTIF('Test Cases'!K2:K147,"Not Run") | D5: =IFERROR(C5/146,0)
B6: Pass | C6: =COUNTIF('Test Cases'!K2:K147,"Pass") | D6: =IFERROR(C6/146,0)
B7: Fail | C7: =COUNTIF('Test Cases'!K2:K147,"Fail") | D7: =IFERROR(C7/146,0)
B8: Blocked | C8: =COUNTIF('Test Cases'!K2:K147,"Blocked") | D8: =IFERROR(C8/146,0)
B9: N/A | C9: =COUNTIF('Test Cases'!K2:K147,"N/A") | D9: =IFERROR(C9/146,0)
B10: TOTAL | C10: 146 | D10: 1
B13: Priority | C13: Total | D13: Passed | E13: % Pass
B14: Critical | C14: =COUNTIF('Test Cases'!D2:D147,"Critical") | D14: =COUNTIFS('Test Cases'!D2:D147,"Critical",'Test Cases'!K2:K147,"Pass") | E14: =IFERROR(D14/C14,0)
B15: High | C15: =COUNTIF('Test Cases'!D2:D147,"High") | D15: =COUNTIFS('Test Cases'!D2:D147,"High",'Test Cases'!K2:K147,"Pass") | E15: =IFERROR(D15/C15,0)
B16: Medium | C16: =COUNTIF('Test Cases'!D2:D147,"Medium") | D16: =COUNTIFS('Test Cases'!D2:D147,"Medium",'Test Cases'!K2:K147,"Pass") | E16: =IFERROR(D16/C16,0)
B17: Low | C17: =COUNTIF('Test Cases'!D2:D147,"Low") | D17: =COUNTIFS('Test Cases'!D2:D147,"Low",'Test Cases'!K2:K147,"Pass") | E17: =IFERROR(D17/C17,0)
B21: Defect Status | C21: Count
B22: Open | C22: =COUNTIF('Defect Log'!F2:F31,"Open")
B23: In Progress | C23: =COUNTIF('Defect Log'!F2:F31,"In Progress")
B24: Fixed | C24: =COUNTIF('Defect Log'!F2:F31,"Fixed")
B25: Verified | C25: =COUNTIF('Defect Log'!F2:F31,"Verified")
B26: Closed | C26: =COUNTIF('Defect Log'!F2:F31,"Closed")
B27: Re-Opened | C27: =COUNTIF('Defect Log'!F2:F31,"Re-Opened")
B28: Wont Fix | C28: =COUNTIF('Defect Log'!F2:F31,"Wont Fix")
B29: Accepted Workaround | C29: =COUNTIF('Defect Log'!F2:F31,"Accepted Workaround")
B32: Sign-Off Readiness
B33: Critical tests passing (must be 100%) | E33: =IFERROR(COUNTIFS('Test Cases'!D2:D147,"Critical",'Test Cases'!K2:K147,"Pass")/COUNTIF('Test Cases'!D2:D147,"Critical"),0)
B34: High tests passing (must be ≥ 95%) | E34: =IFERROR(COUNTIFS('Test Cases'!D2:D147,"High",'Test Cases'!K2:K147,"Pass")/COUNTIF('Test Cases'!D2:D147,"High"),0)
B35: Open Critical/High defects (must be 0) | E35: =COUNTIFS('Defect Log'!E2:E31,"Critical",'Defect Log'!F2:F31,"Open")+COUNTIFS('Defect Log'!E2:E31,"High",'Defect Log'!F2:F31,"Open")
